kraken_core/__init__.py
kraken_core/kraken_core.py
kraken_core_sdk-2021.12.9.1639037700.dist-info/METADATA
kraken_core_sdk-2021.12.9.1639037700.dist-info/WHEEL
kraken_core_sdk-2021.12.9.1639037700.dist-info/top_level.txt
kraken_core_sdk-2021.12.9.1639037700.dist-info/RECORD
